myprayer/__init__.py
myprayer/cli/config.py
myprayer/cli/constants.py
myprayer/cli/day.py
myprayer/cli/enums.py
myprayer/cli/main.py
myprayer/cli/output.py
myprayer/cli/utils.py
myprayer-3.2.0.dist-info/LICENSE
myprayer-3.2.0.dist-info/METADATA
myprayer-3.2.0.dist-info/WHEEL
myprayer-3.2.0.dist-info/entry_points.txt
myprayer-3.2.0.dist-info/RECORD
