Metadata-Version: 2.1
Name: myprayer
Version: 3.2.0
Summary: A CLI tool to get prayer times
Home-page: https://github.com/YoussefAswad/myprayer
License: MIT
Author: Youssef Aswad
Author-email: youssefaswad@gmail.com
Requires-Python: >=3.8,<4.0
Classifier: License :: OSI Approved :: MIT License
Classifier: Programming Language :: Python :: 3
Classifier: Programming Language :: Python :: 3.8
Classifier: Programming Language :: Python :: 3.9
Classifier: Programming Language :: Python :: 3.10
Classifier: Programming Language :: Python :: 3.11
Classifier: Programming Language :: Python :: 3.12
Requires-Dist: adhanpy (>=1.0.5,<2.0.0)
Requires-Dist: geopy (>=2.4.1,<3.0.0)
Requires-Dist: inquirer (>=3.1.3,<4.0.0)
Requires-Dist: pydantic (>=2.5.3,<3.0.0)
Requires-Dist: rich (>=13.6.0,<14.0.0)
Requires-Dist: typer (>=0.9.0,<0.10.0)
Requires-Dist: tzdata (>=2024.1,<2025.0)
Requires-Dist: tzlocal (>=5.2,<6.0)
Project-URL: Repository, https://github.com/YoussefAswad/myprayer
